[
    {
      "question": "Inside which HTML element do we put the JavaScript??",
      "choice1": "A. <script>",
      "choice2": "B. <javascript>",
      "choice3": "C. <js>",
      "choice4": "D. <scripting>",
      "answer": 1
    },
    {
      "question": "What is the correct syntax for referring to an external script called 'xxx.js'?",
      "choice1": "A. <script href='xxx.js'>",
      "choice2": "B. <script name='xxx.js'>",
      "choice3": "C. <script src='xxx.js'>",
      "choice4": "D. <script file='xxx.js'>",
      "answer": 3
    },
    {
      "question": " How do you write 'Hello World' in an alert box?",
      "choice1": "A. msgBox('Hello World');",
      "choice2": "B. alertBox('Hello World');",
      "choice3": "C. msg('Hello World');",
      "choice4": "D. alert('Hello World');",
      "answer": 4
    },
    {
      "question": "Inside which HTML element do we put the JavaScript??",
      "choice1": "A. <script>",
      "choice2": "B. <javascript>",
      "choice3": "C. <js>",
      "choice4": "D. <scripting>",
      "answer": 1
    },
    {
      "question": "What is the correct syntax for referring to an external script called 'xxx.js'?",
      "choice1": "A. <script href='xxx.js'>",
      "choice2": "B. <script name='xxx.js'>",
      "choice3": "C. <script src='xxx.js'>",
      "choice4": "D. <script file='xxx.js'>",
      "answer": 3
    },
    {
      "question": " How do you write 'Hello World' in an alert box?",
      "choice1": "A. msgBox('Hello World');",
      "choice2": "B. alertBox('Hello World');",
      "choice3": "C. msg('Hello World');",
      "choice4": "D. alert('Hello World');",
      "answer": 4
    }
  ]